subsql_pg/__init__.py
subsql_pg/pgdriver.py
subsql_pg-0.0.1.dist-info/METADATA
subsql_pg-0.0.1.dist-info/WHEEL
subsql_pg-0.0.1.dist-info/top_level.txt
subsql_pg-0.0.1.dist-info/RECORD
